{
  "posts": [
    {
      "id": 1,
      "name": "soldiers",
      "number": 81370
    },
    {
      "id": 2,
      "name": "tanks",
      "number": 2848
    },
    {
      "id": 3,
      "name": "armoured personnel vehicle",
      "number": 5748
    },
    {
      "id": 4,
      "name": "artillery systems",
      "number": 1839
    },
    {
      "id": 5,
      "name": "MLRS",
      "number": 393
    },
    {
      "id": 6,
      "name": "anti-aircraft warfare systems",
      "number": 206
    },
    {
      "id": 7,
      "name": "aircraft",
      "number": 278
    },
    {
      "id": 8,
      "name": "helicopters",
      "number": 261
    },
    {
      "id": 9,
      "name": "UAV",
      "number": 1509
    },
    {
      "id": 10,
      "name": "warships",
      "number": 16
    },
    {
      "id": 11,
      "name": "vehicles",
      "number": 4316
    }
  ],
  "profile": {
    "name": "typicode"
  }
}
